{
  "total": 375853,
  "number": 46300,
  "lower": 124705,
  "upper": 3695,
  "special": 12,
  "number_lower": 179233,
  "number_upper": 6250,
  "number_special": 59,
  "lower_upper": 3281,
  "lower_special": 393,
  "upper_special": 14,
  "no_number": 47,
  "no_lower": 34,
  "no_upper": 637,
  "no_special": 10852,
  "mean": 8.604808262804873,
  "nb_words_by_length": {
    "6": 27269,
    "2": 21,
    "8": 68207,
    "3": 111,
    "4": 846,
    "5": 9198,
    "7": 73545,
    "9": 93462,
    "10": 49671,
    "11": 36324,
    "12": 8228,
    "13": 4739,
    "14": 2250,
    "15": 1216,
    "16": 691,
    "19": 7,
    "21": 4,
    "26": 1,
    "35": 1,
    "37": 1,
    "47": 1,
    "72": 1,
    "91": 1,
    "103": 1,
    "111": 1,
    "17": 29,
    "22": 3,
    "18": 20,
    "20": 4
  }
}
